setup.py
pyphp/__init__.py
pyphp/compiler.py
pyphp/errors.py
pyphp/executer.py
pyphp/parser.py
pyphp/phparray.py
pyphp/phpbuiltins.py
pyphp/phpclass.py
pyphp/phpfunction.py
pyphp/pyphp.py
pyphp/scope.py
pyphp/trace.py
pyphp/varref.py
pyphp.egg-info/PKG-INFO
pyphp.egg-info/SOURCES.txt
pyphp.egg-info/dependency_links.txt
pyphp.egg-info/not-zip-safe
pyphp.egg-info/top_level.txt