Metadata-Version: 1.0
Name: pyphp
Version: 0.1
Summary: Php parser, compiler and interpreter, in python
Home-page: https://github.com/g-i-o-/pyphp
Author: Giovany Vega
Author-email: aleph.omega@gmail.com
License: MIT
Platform: UNKNOWN
